[
  {
    "id": "ios_13416340734",
    "platform": "ios",
    "author": "HieuNg4438",
    "date": "2025-11-21T03:07:58.338Z",
    "rating": 5,
    "title": "Dịch vụ tốt",
    "text": "Luôn có xe",
    "version": "3.6.161",
    "device": "iOS",
    "replyDate": null,
    "replyText": null,
    "sentiment": {
      "score": 1,
      "label": "positive"
    },
    "categories": [
      "general"
    ]
  },
  {
    "id": "ios_13416151469",
    "platform": "ios",
    "author": "thongdau",
    "date": "2025-11-21T03:07:58.338Z",
    "rating": 1,
    "title": "Quá tệ",
    "text": "App lỏ cực kì",
    "version": "3.6.161",
    "device": "iOS",
    "replyDate": null,
    "replyText": null,
    "sentiment": {
      "score": -1,
      "label": "negative"
    },
    "categories": [
      "general"
    ]
  },
  {
    "id": "ios_13415997670",
    "platform": "ios",
    "author": "Ty Si",
    "date": "2025-11-21T03:07:58.338Z",
    "rating": 5,
    "title": "Đánh giá",
    "text": "Rẻ oki",
    "version": "3.6.161",
    "device": "iOS",
    "replyDate": null,
    "replyText": null,
    "sentiment": {
      "score": 1,
      "label": "positive"
    },
    "categories": [
      "pricing"
    ]
  },
  {
    "id": "ios_13415969688",
    "platform": "ios",
    "author": "Thanh2229",
    "date": "2025-11-21T03:07:58.338Z",
    "rating": 1,
    "title": "Giao hàng kém",
    "text": "ko xử dụng dc tính năng giao hàng cứ bị lỗi",
    "version": "3.6.161",
    "device": "iOS",
    "replyDate": null,
    "replyText": null,
    "sentiment": {
      "score": -1,
      "label": "negative"
    },
    "categories": [
      "features",
      "bugs"
    ]
  },
  {
    "id": "ios_13415918221",
    "platform": "ios",
    "author": "Bi6394",
    "date": "2025-11-21T03:07:58.338Z",
    "rating": 2,
    "title": "Gần đây app quá nhiều lỗi",
    "text": "Cứ vào lâu lâu là bị treo app, xoay mãi dù 4g wifi lướt web vèo vèo, phải xoá app tải lại mới hết. Đã thế còn lỗi thông báo cả mấy chục lần cùng nội dung rất phiền. Quyết định xoá app đổi ứng dụng dịch vụ khác dùng cho đỡ nhọc",
    "version": "3.6.161",
    "device": "iOS",
    "replyDate": null,
    "replyText": null,
    "sentiment": {
      "score": -0.6,
      "label": "negative"
    },
    "categories": [
      "performance",
      "bugs",
      "notification",
      "update"
    ]
  },
  {
    "id": "ios_13415709974",
    "platform": "ios",
    "author": "Gloryhuong",
    "date": "2025-11-21T03:07:58.338Z",
    "rating": 1,
    "title": "Phản hồi khách hàng rất chậm, tự động thu thêm 30k của khách",
    "text": "Dịch vụ vô cùng tệ",
    "version": "3.6.161",
    "device": "iOS",
    "replyDate": null,
    "replyText": null,
    "sentiment": {
      "score": -1,
      "label": "negative"
    },
    "categories": [
      "performance"
    ]
  },
  {
    "id": "ios_13415390647",
    "platform": "ios",
    "author": "Baby girl ko sợ cô đơn",
    "date": "2025-11-21T03:07:58.338Z",
    "rating": 5,
    "title": "Xe đón nhanh , tuyệt vời",
    "text": "Xe đón nhanh , dịch vụ tuyệt vời",
    "version": "3.6.161",
    "device": "iOS",
    "replyDate": null,
    "replyText": null,
    "sentiment": {
      "score": 1,
      "label": "positive"
    },
    "categories": [
      "general"
    ]
  },
  {
    "id": "ios_13415132087",
    "platform": "ios",
    "author": "_lynh201_",
    "date": "2025-11-21T03:07:58.338Z",
    "rating": 1,
    "title": "không hoàn tiền cho khách hàng",
    "text": "app đặt xe không có xe nhận, huỷ chuyến xong không hoàn tiền, gửi yêu cầu liên tục vẫn không nhận được hoàn phí, liên tục báo đóng yêu cầu do quá tải,",
    "version": "3.6.161",
    "device": "iOS",
    "replyDate": null,
    "replyText": null,
    "sentiment": {
      "score": -0.9,
      "label": "negative"
    },
    "categories": [
      "features"
    ]
  },
  {
    "id": "ios_13415106967",
    "platform": "ios",
    "author": "Bí Đỏ Hớn Hờ",
    "date": "2025-11-21T03:07:58.338Z",
    "rating": 2,
    "title": "sửa",
    "text": "mong be cho phép mở khoá tào khoản",
    "version": "3.6.161",
    "device": "iOS",
    "replyDate": null,
    "replyText": null,
    "sentiment": {
      "score": -0.5,
      "label": "negative"
    },
    "categories": [
      "bugs"
    ]
  },
  {
    "id": "ios_13412832097",
    "platform": "ios",
    "author": "Say Hi~",
    "date": "2025-11-21T03:07:58.338Z",
    "rating": 4,
    "title": "APP",
    "text": "Sao app nay nhìn cứ Fake sao ý. Cứ cùi cùi",
    "version": "3.6.160",
    "device": "iOS",
    "replyDate": null,
    "replyText": null,
    "sentiment": {
      "score": 0.5,
      "label": "positive"
    },
    "categories": [
      "general"
    ]
  },
  {
    "id": "ios_13412506230",
    "platform": "ios",
    "author": "Dr. D 3488",
    "date": "2025-11-21T03:07:58.338Z",
    "rating": 1,
    "title": "App ít tài xê, không sử dụng được nếu đi tỉnh lẻ",
    "text": "Cần cải.thiện nhiều tài hơn",
    "version": "3.6.160",
    "device": "iOS",
    "replyDate": null,
    "replyText": null,
    "sentiment": {
      "score": -1,
      "label": "negative"
    },
    "categories": [
      "general"
    ]
  },
  {
    "id": "ios_13412220912",
    "platform": "ios",
    "author": "Sava397",
    "date": "2025-11-21T03:07:58.338Z",
    "rating": 1,
    "title": "Terrible",
    "text": "Drivers canceled twice with a crazy prices, why they accept and then cancel ???? Why the app doesn’t give u discount for the next ride if the driver cancel the trip ????? Price x2, motorbike are so bad but price is crazy ! Delete and use Xanh taxi, always great service not like a Be, 0 starts from a million",
    "version": "3.6.160",
    "device": "iOS",
    "replyDate": null,
    "replyText": null,
    "sentiment": {
      "score": -1,
      "label": "negative"
    },
    "categories": [
      "general"
    ]
  },
  {
    "id": "ios_13412032440",
    "platform": "ios",
    "author": "carrot052",
    "date": "2025-11-21T03:07:58.338Z",
    "rating": 1,
    "title": "Huỷ chuyến tuỳ tiện",
    "text": "đã đặt trước r còn huỷ chuyến của khach, lỡ giờ mất thời gian",
    "version": "3.6.160",
    "device": "iOS",
    "replyDate": null,
    "replyText": null,
    "sentiment": {
      "score": -0.9,
      "label": "negative"
    },
    "categories": [
      "general"
    ]
  },
  {
    "id": "ios_13411526915",
    "platform": "ios",
    "author": "lkgamr",
    "date": "2025-11-21T03:07:58.338Z",
    "rating": 1,
    "title": "thủ tục lạc hậu",
    "text": "thời đại nào rồi còn bắt người mới liên kết cái này cái kia",
    "version": "3.6.160",
    "device": "iOS",
    "replyDate": null,
    "replyText": null,
    "sentiment": {
      "score": -1,
      "label": "negative"
    },
    "categories": [
      "update"
    ]
  },
  {
    "id": "ios_13411391618",
    "platform": "ios",
    "author": "huynhminhhoang.bmt",
    "date": "2025-11-21T03:07:58.338Z",
    "rating": 5,
    "title": "Review",
    "text": "Well done",
    "version": "3.6.160",
    "device": "iOS",
    "replyDate": null,
    "replyText": null,
    "sentiment": {
      "score": 1,
      "label": "positive"
    },
    "categories": [
      "general"
    ]
  },
  {
    "id": "ios_13411286606",
    "platform": "ios",
    "author": "Ahdnwncha",
    "date": "2025-11-21T03:07:58.338Z",
    "rating": 2,
    "title": "Phản ánh",
    "text": "Thật tệ khi phải nói lời chia tay đến bee, tôi là tài xế bike hôm nay có đến văn phòng để làm việc về vấn đề tài khoảng bị khoá, nhân viên hỗ trợ rườm rà không nói rõ khi mở lại cần gì cần gì mà mỗi lần đến là phát sinh thêm một cái khác làm tôi rất bực mình vì nhà ở xa, rất tiếc phải nói lời tạm biệt",
    "version": "3.6.160",
    "device": "iOS",
    "replyDate": null,
    "replyText": null,
    "sentiment": {
      "score": -0.6,
      "label": "negative"
    },
    "categories": [
      "bugs",
      "account",
      "driver"
    ]
  },
  {
    "id": "ios_13411186942",
    "platform": "ios",
    "author": "markieaustra",
    "date": "2025-11-21T03:07:58.338Z",
    "rating": 5,
    "title": "Ok",
    "text": "Ok",
    "version": "3.6.160",
    "device": "iOS",
    "replyDate": null,
    "replyText": null,
    "sentiment": {
      "score": 1,
      "label": "positive"
    },
    "categories": [
      "general"
    ]
  },
  {
    "id": "ios_13410985951",
    "platform": "ios",
    "author": "eisuujr",
    "date": "2025-11-21T03:07:58.338Z",
    "rating": 1,
    "title": "Tài xế rác",
    "text": "Tài xế toàn trò nhận cuốc xong đi xa vị trí nhận làm mất thời gian khách hàng",
    "version": "3.6.160",
    "device": "iOS",
    "replyDate": null,
    "replyText": null,
    "sentiment": {
      "score": -1,
      "label": "negative"
    },
    "categories": [
      "driver"
    ]
  },
  {
    "id": "ios_13410678136",
    "platform": "ios",
    "author": "Khachhangf",
    "date": "2025-11-21T03:07:58.338Z",
    "rating": 1,
    "title": "BE không hỗ trợ khách hàng",
    "text": "Tài xế ok nhưng Be lại ko ok với khách hàng, khách hàng cần hỗ trợ Be ko hỗ trợ và không có lời giải thích chính đáng cho khách",
    "version": "3.6.160",
    "device": "iOS",
    "replyDate": null,
    "replyText": null,
    "sentiment": {
      "score": -0.9,
      "label": "negative"
    },
    "categories": [
      "driver"
    ]
  },
  {
    "id": "ios_13408938679",
    "platform": "ios",
    "author": "lntmntml",
    "date": "2025-11-21T03:07:58.338Z",
    "rating": 3,
    "title": "Chưa hài lòng lắm",
    "text": "Phản hồi của khách giải quyết còn chậm.",
    "version": "3.6.160",
    "device": "iOS",
    "replyDate": null,
    "replyText": null,
    "sentiment": {
      "score": 0,
      "label": "neutral"
    },
    "categories": [
      "performance"
    ]
  },
  {
    "id": "ios_13408442220",
    "platform": "ios",
    "author": "☺️🥲🥲🥲☺️☺️☺️☺️🥲",
    "date": "2025-11-21T03:07:58.338Z",
    "rating": 1,
    "title": "Lỗi thanh toán",
    "text": "Đặt sớm nhưng do tài xế huỷ phải đặt lại và đắt hơn rất nhiều?",
    "version": "3.6.160",
    "device": "iOS",
    "replyDate": null,
    "replyText": null,
    "sentiment": {
      "score": -1,
      "label": "negative"
    },
    "categories": [
      "bugs",
      "driver",
      "payment"
    ]
  },
  {
    "id": "ios_13408442185",
    "platform": "ios",
    "author": "ngdungbechan123",
    "date": "2025-11-21T03:07:58.338Z",
    "rating": 1,
    "title": "tệ",
    "text": "tệ, khách hàng thân thiết nhưng chính sách hoàn trả quá kém",
    "version": "3.6.160",
    "device": "iOS",
    "replyDate": null,
    "replyText": null,
    "sentiment": {
      "score": -1,
      "label": "negative"
    },
    "categories": [
      "general"
    ]
  },
  {
    "id": "ios_13407800680",
    "platform": "ios",
    "author": "ZoeDoan",
    "date": "2025-11-21T03:07:58.338Z",
    "rating": 1,
    "title": "Không bao giờ sử dụng DV app Be",
    "text": "Không xử lý vấn đề khách hàng.",
    "version": "3.6.160",
    "device": "iOS",
    "replyDate": null,
    "replyText": null,
    "sentiment": {
      "score": -1,
      "label": "negative"
    },
    "categories": [
      "bugs"
    ]
  },
  {
    "id": "ios_13407643581",
    "platform": "ios",
    "author": "Shrimzyyyyy",
    "date": "2025-11-21T03:07:58.338Z",
    "rating": 5,
    "title": "Be rất oke",
    "text": "Mình dùng be mấy năm rồi sài rất oke tài xế nhiều đặt xe dễ và tài xế chạy rất cẩn thận và vui vẻ",
    "version": "3.6.160",
    "device": "iOS",
    "replyDate": null,
    "replyText": null,
    "sentiment": {
      "score": 1,
      "label": "positive"
    },
    "categories": [
      "features",
      "driver"
    ]
  },
  {
    "id": "ios_13407580065",
    "platform": "ios",
    "author": "Người dùng Be❤️",
    "date": "2025-11-21T03:07:58.338Z",
    "rating": 1,
    "title": "Dịch vụ hoàn tiền cuốc bị huỷ",
    "text": "Không hoàn trả đủ tiền cho khách",
    "version": "3.6.160",
    "device": "iOS",
    "replyDate": null,
    "replyText": null,
    "sentiment": {
      "score": -1,
      "label": "negative"
    },
    "categories": [
      "general"
    ]
  },
  {
    "id": "ios_13407080528",
    "platform": "ios",
    "author": "my u de",
    "date": "2025-11-21T03:07:58.338Z",
    "rating": 1,
    "title": "Cách hoạt động về đặt trc",
    "text": "bên be không quan tâm đến trải nghiêm khác hàng",
    "version": "3.6.160",
    "device": "iOS",
    "replyDate": null,
    "replyText": null,
    "sentiment": {
      "score": -1,
      "label": "negative"
    },
    "categories": [
      "general"
    ]
  },
  {
    "id": "ios_13405628045",
    "platform": "ios",
    "author": "Chii chành chành",
    "date": "2025-11-21T03:07:58.338Z",
    "rating": 1,
    "title": "Phê bình app",
    "text": "Hôm 16/11 mình có đặt xe đi lúc 3h20 sáng vì mình có cv đột xuất mình đặt xe máy và mình có bảo chờ mình 1 chút để mình lấy nốt đồ cần thiết r mình ra vậy mà shipper chửi mình xúc phạm bame mình rất nặng rồi bỏ đi thật sự rất bức xúc về vấn đề chửi khách quá đáng như vậy",
    "version": "3.6.160",
    "device": "iOS",
    "replyDate": null,
    "replyText": null,
    "sentiment": {
      "score": -1,
      "label": "negative"
    },
    "categories": [
      "features",
      "bugs"
    ]
  },
  {
    "id": "ios_13405284541",
    "platform": "ios",
    "author": "Tinn273",
    "date": "2025-11-21T03:07:58.338Z",
    "rating": 5,
    "title": "IU/UX",
    "text": "Đã cấp full quyền nhưng không cập nhật thời gian realtime trên NotiCen ở màn hình khoá;\nDynamic island không linh hoạt, luôn hiển thị full thanh chiếm màn hình.",
    "version": "3.6.160",
    "device": "iOS",
    "replyDate": null,
    "replyText": null,
    "sentiment": {
      "score": 1,
      "label": "positive"
    },
    "categories": [
      "security",
      "update"
    ]
  },
  {
    "id": "ios_13403720810",
    "platform": "ios",
    "author": "Bảo anh khang",
    "date": "2025-11-21T03:07:58.338Z",
    "rating": 3,
    "title": "Nhiều Tài xế chậm",
    "text": "Đặt 3 lần mới được 1 bác tài .",
    "version": "3.6.160",
    "device": "iOS",
    "replyDate": null,
    "replyText": null,
    "sentiment": {
      "score": -0.1,
      "label": "neutral"
    },
    "categories": [
      "performance",
      "update",
      "driver"
    ]
  },
  {
    "id": "ios_13403500801",
    "platform": "ios",
    "author": "Tậken",
    "date": "2025-11-21T03:07:58.338Z",
    "rating": 5,
    "title": "AKOM.VN",
    "text": "AK",
    "version": "3.6.160",
    "device": "iOS",
    "replyDate": null,
    "replyText": null,
    "sentiment": {
      "score": 1,
      "label": "positive"
    },
    "categories": [
      "general"
    ]
  },
  {
    "id": "ios_13402730586",
    "platform": "ios",
    "author": "Huy Libra",
    "date": "2025-11-21T03:07:58.338Z",
    "rating": 2,
    "title": "Giao diện ứng dụng",
    "text": "Sao khi thay đổi giao diện trang chủ bên trong ứng dụng khó xài kinh khủng, muốn đặt giao hàng tìm chẳng ra",
    "version": "3.6.160",
    "device": "iOS",
    "replyDate": null,
    "replyText": null,
    "sentiment": {
      "score": -0.7,
      "label": "negative"
    },
    "categories": [
      "ui",
      "update"
    ]
  },
  {
    "id": "ios_13401319185",
    "platform": "ios",
    "author": "đội cực nhanh",
    "date": "2025-11-21T03:07:58.338Z",
    "rating": 5,
    "title": "tuyệt vời",
    "text": "tuyệt vời",
    "version": "3.6.160",
    "device": "iOS",
    "replyDate": null,
    "replyText": null,
    "sentiment": {
      "score": 1,
      "label": "positive"
    },
    "categories": [
      "general"
    ]
  },
  {
    "id": "ios_13400703129",
    "platform": "ios",
    "author": "Hatehfuv",
    "date": "2025-11-21T03:07:58.338Z",
    "rating": 1,
    "title": "Cái vớ vẩn nhất là có rate khách.",
    "text": "Ngay cả k làm j sai. Gặp mấy tk vớ vẩn khách cũng sẽ bị ảnh hưởng",
    "version": "3.6.160",
    "device": "iOS",
    "replyDate": null,
    "replyText": null,
    "sentiment": {
      "score": -0.9,
      "label": "negative"
    },
    "categories": [
      "general"
    ]
  },
  {
    "id": "ios_13400499194",
    "platform": "ios",
    "author": "Qkajsjjjf",
    "date": "2025-11-21T03:07:58.338Z",
    "rating": 1,
    "title": "Ghim vị trí quá ngu",
    "text": "Ghim vị trí quá ngu",
    "version": "3.6.160",
    "device": "iOS",
    "replyDate": null,
    "replyText": null,
    "sentiment": {
      "score": -1,
      "label": "negative"
    },
    "categories": [
      "general"
    ]
  },
  {
    "id": "ios_13399662034",
    "platform": "ios",
    "author": "student0805",
    "date": "2025-11-21T03:07:58.338Z",
    "rating": 1,
    "title": "Tệ",
    "text": "Đợi quá lâu, tài xế liên tục huỷ, cực kì không hài lòng",
    "version": "3.6.160",
    "device": "iOS",
    "replyDate": null,
    "replyText": null,
    "sentiment": {
      "score": -1,
      "label": "negative"
    },
    "categories": [
      "driver"
    ]
  },
  {
    "id": "ios_13399472165",
    "platform": "ios",
    "author": "Cửa hàng trà sữa",
    "date": "2025-11-21T03:07:58.338Z",
    "rating": 1,
    "title": "định vị sai",
    "text": "Áp định vị bị sai chỉ có 1 số của 1 con đường mà định vị sai tùm lum. Rất phiền hà cho khách hàng",
    "version": "3.6.160",
    "device": "iOS",
    "replyDate": null,
    "replyText": null,
    "sentiment": {
      "score": -1,
      "label": "negative"
    },
    "categories": [
      "general"
    ]
  },
  {
    "id": "ios_13399420862",
    "platform": "ios",
    "author": "Josephha.",
    "date": "2025-11-21T03:07:58.338Z",
    "rating": 1,
    "title": "Chính sách rất rất tệ - Very bad policy",
    "text": "Thời tiết mưa rất lớn, đặt xe ko có tài nhận hoặc có tài ở rất xa vài cây số nên phải tìm tài xế mới. Hệ thống ghi nhận là Huỷ chuyến nhiều lần và khoá tài khoản ko thể mở lại…. !",
    "version": "3.6.160",
    "device": "iOS",
    "replyDate": null,
    "replyText": null,
    "sentiment": {
      "score": -1,
      "label": "negative"
    },
    "categories": [
      "features",
      "account",
      "update",
      "driver"
    ]
  },
  {
    "id": "ios_13399367876",
    "platform": "ios",
    "author": "Trân phát xít",
    "date": "2025-11-21T03:07:58.338Z",
    "rating": 3,
    "title": "tài xế",
    "text": "tài xế gì đặt toàn huỷ chuyến,bộ chê gần ít tiền hay gì v trời",
    "version": "3.6.160",
    "device": "iOS",
    "replyDate": null,
    "replyText": null,
    "sentiment": {
      "score": 0,
      "label": "neutral"
    },
    "categories": [
      "driver"
    ]
  },
  {
    "id": "ios_13396570927",
    "platform": "ios",
    "author": "trinhminhduc",
    "date": "2025-11-21T03:07:58.338Z",
    "rating": 5,
    "title": "Nhận xét",
    "text": "App tiện lợi hơn mấy app khác là có đặt trc",
    "version": "3.6.160",
    "device": "iOS",
    "replyDate": null,
    "replyText": null,
    "sentiment": {
      "score": 1,
      "label": "positive"
    },
    "categories": [
      "general"
    ]
  },
  {
    "id": "ios_13396353461",
    "platform": "ios",
    "author": "Óc chó đường lưỡi bò",
    "date": "2025-11-21T03:07:58.338Z",
    "rating": 1,
    "title": "Bực bội",
    "text": "Sao sáng nay tôi đặt xe đã có xế rồi nhưng app vẫn báo có xế và nhảy ra màn hình chuyến đi hoài, tôi không thể đặt giao hàng khi app cứ nhảy vào màn hình chuyến đi và báo thông báo hoài, tôi rất không hài lòng",
    "version": "3.6.160",
    "device": "iOS",
    "replyDate": null,
    "replyText": null,
    "sentiment": {
      "score": -1,
      "label": "negative"
    },
    "categories": [
      "features",
      "notification"
    ]
  },
  {
    "id": "ios_13396338705",
    "platform": "ios",
    "author": "hẹueodhdvdi",
    "date": "2025-11-21T03:07:58.338Z",
    "rating": 1,
    "title": "Tiêu cực",
    "text": "dịch vụ quá tệ bị huỷ quá nhiều lần đợi quá lâu",
    "version": "3.6.160",
    "device": "iOS",
    "replyDate": null,
    "replyText": null,
    "sentiment": {
      "score": -1,
      "label": "negative"
    },
    "categories": [
      "general"
    ]
  },
  {
    "id": "ios_13396315343",
    "platform": "ios",
    "author": "Hkanshmss",
    "date": "2025-11-21T03:07:58.338Z",
    "rating": 1,
    "title": "tiêu cực",
    "text": "đợi cho đã rồi huỷ quá nhiều lần",
    "version": "3.6.160",
    "device": "iOS",
    "replyDate": null,
    "replyText": null,
    "sentiment": {
      "score": -1,
      "label": "negative"
    },
    "categories": [
      "general"
    ]
  },
  {
    "id": "ios_13396198894",
    "platform": "ios",
    "author": "NguyenTien",
    "date": "2025-11-21T03:07:58.338Z",
    "rating": 1,
    "title": "Tổng Đài Chăm Sóc Khách Hàng và App Khiếu Nại Mất Hàng Cực Kì Tệ",
    "text": "Shipper gửi nhầm địa chỉ, ko gọi người nhận. Tự ý giao người khác! Người nhận cần gấp món hàng mà gọi tổng đài 10 cuộc ko bắt máy, liên hệ chat khẩn ko ai trả lời... Dịch vụ xử lý cực tệ! Ko cách nào liên lạc được shipper",
    "version": "3.6.160",
    "device": "iOS",
    "replyDate": null,
    "replyText": null,
    "sentiment": {
      "score": -1,
      "label": "negative"
    },
    "categories": [
      "general"
    ]
  },
  {
    "id": "ios_13396159374",
    "platform": "ios",
    "author": "bunny1257@",
    "date": "2025-11-21T03:07:58.338Z",
    "rating": 1,
    "title": "THÁI ĐỘ TÀI XẾ TỆ",
    "text": "Tài xế thái độ, khinh thường và đe doạ tính mạng khách",
    "version": "3.6.160",
    "device": "iOS",
    "replyDate": null,
    "replyText": null,
    "sentiment": {
      "score": -1,
      "label": "negative"
    },
    "categories": [
      "driver"
    ]
  },
  {
    "id": "ios_13396063958",
    "platform": "ios",
    "author": "Không nên dùng be, tẩy chay",
    "date": "2025-11-21T03:07:58.338Z",
    "rating": 1,
    "title": "Quá tệ",
    "text": "Không nên dùng, tài xế và app coi thường khách hàng",
    "version": "3.6.160",
    "device": "iOS",
    "replyDate": null,
    "replyText": null,
    "sentiment": {
      "score": -1,
      "label": "negative"
    },
    "categories": [
      "driver"
    ]
  },
  {
    "id": "ios_13396021106",
    "platform": "ios",
    "author": "anhn31664",
    "date": "2025-11-21T03:07:58.338Z",
    "rating": 1,
    "title": "Lừa đảo",
    "text": "Ứng dụng cho sd voucher nhưng lừa tiền khách hàng",
    "version": "3.6.160",
    "device": "iOS",
    "replyDate": null,
    "replyText": null,
    "sentiment": {
      "score": -1,
      "label": "negative"
    },
    "categories": [
      "promotion"
    ]
  },
  {
    "id": "ios_13395984810",
    "platform": "ios",
    "author": "gấu bông 10",
    "date": "2025-11-21T03:07:58.338Z",
    "rating": 5,
    "title": "Be không hoàn tiền khi đơn đặt bị lỗi.",
    "text": "Những ngày khác đều ok. Riêng ngày hôm nay be load chậm cực kì. Chưa kể đơn ngày 11/11 đặt bị lỗi mà vẫn trừ tiền mình, mình khiếu nại vẫn không hoàn tiền. Mình biết mấy chục ngàn không tới đâu nhưng be làm vậy là không được.",
    "version": "3.6.160",
    "device": "iOS",
    "replyDate": null,
    "replyText": null,
    "sentiment": {
      "score": 0.8,
      "label": "positive"
    },
    "categories": [
      "performance",
      "bugs"
    ]
  },
  {
    "id": "ios_13395893282",
    "platform": "ios",
    "author": "dịdff đg hzhzhz",
    "date": "2025-11-21T03:07:58.338Z",
    "rating": 1,
    "title": "Qq",
    "text": "Qq",
    "version": "3.6.160",
    "device": "iOS",
    "replyDate": null,
    "replyText": null,
    "sentiment": {
      "score": -1,
      "label": "negative"
    },
    "categories": [
      "general"
    ]
  },
  {
    "id": "ios_13395888314",
    "platform": "ios",
    "author": "Việt dũng trần",
    "date": "2025-11-21T03:07:58.338Z",
    "rating": 1,
    "title": "Ứng dụng lag lỗi dù đã cập nhật",
    "text": "Quá lag và tbao hiện liên tục lặp đi lặp lại k dừng dc",
    "version": "3.6.160",
    "device": "iOS",
    "replyDate": null,
    "replyText": null,
    "sentiment": {
      "score": -1,
      "label": "negative"
    },
    "categories": [
      "performance",
      "bugs",
      "update"
    ]
  },
  {
    "id": "ios_13395879011",
    "platform": "ios",
    "author": "Diva Shop",
    "date": "2025-11-21T03:07:58.338Z",
    "rating": 1,
    "title": "Tệ",
    "text": "App đặt đơn xong load chậm và nhảy tùm lum",
    "version": "3.6.160",
    "device": "iOS",
    "replyDate": null,
    "replyText": null,
    "sentiment": {
      "score": -1,
      "label": "negative"
    },
    "categories": [
      "performance"
    ]
  }
]